<?xml version="1.0" encoding="UTF-8"?>
<extension version="2.5" type="plugin" group="system" method="upgrade">
	<name>plg_system_jinboundleadmap</name>
    <creationDate>March 13 2018</creationDate>
    <author>Joomlashack</author>
    <authorEmail>help@joomlashack.com</authorEmail>
    <authorUrl>http://joomlashack.com</authorUrl>
    <copyright>Copyright (c) 2006-2012 Anything-Digital.com - 2016-2017 Open Source Training, LLC</copyright>
    <license>GNU/GPL</license>
    <version>3.0.0a1</version>
	<description>PLG_SYSTEM_JINBOUNDLEADMAP_XML_DESCRIPTION</description>
	<scriptfile>jinboundleadmap.install.php</scriptfile>
	<updateservers>
		<server type="collection" name="plg_system_jinboundleadmap">https://jinbound.com/index.php?option=com_ars&amp;view=update&amp;task=category&amp;id=plugins&amp;format=xml&amp;dummy=extension.xml</server>
		<server type="extension" name="plg_system_jinboundleadmap">https://jinbound.com/index.php?option=com_ars&amp;view=update&amp;task=stream&amp;id=13&amp;format=xml&amp;dummy=extension.xml</server>
	</updateservers>
	<languages folder="language">
		<language tag="en-GB">en-GB/en-GB.plg_system_jinboundleadmap.sys.ini</language>
	</languages>
	<files>
		<filename plugin="jinboundleadmap">jinboundleadmap.php</filename>
		<filename plugin="jinboundleadmap">jinboundleadmap.install.php</filename>
		<filename>forms/filter_leadmap.xml</filename>
		<filename>language/en-GB/en-GB.plg_system_jinboundleadmap.sys.ini</filename>
		<filename>lib/geoip2.phar</filename>
		<filename>tmpl/default.php</filename>
		<filename>tmpl/default_filterbar.php</filename>
	</files>
	<media destination="jinboundleadmap" folder="media">
		<filename>css/leadmap.css</filename>
		<filename>js/StyledMarker.js</filename>
	</media>
	<config>
		<fields name="params">
			<fieldset name="basic">
			</fieldset>
		</fields>
	</config>
</extension>
